{"GameObject":[{"UID":12531780,"ParentUID":0,"TransformType":0,"Name":"Scene","Components":[{"Type":-1,"GameObject UID":12531780,"Translation":[0,0,0],"Rotation":[1,0,0,0],"Scale":[1,1,1],"Enable":true}]},{"UID":596694698,"ParentUID":12531780,"TransformType":0,"Name":"Camera Main","Components":[{"Type":-1,"GameObject UID":596694698,"Translation":[0,0,0],"Rotation":[1,0,0,0],"Scale":[1,1,1],"Enable":true},{"Type":3,"GameObject UID":true,"Enable":true,"Vertical FOV":1,"Windows aspect ratio":1.7777777910232544,"Frustrum Up":[0,1,0],"Frustrum Front":[0,0,1],"Frustrum Pos":[0,0,0]}]},{"UID":1655619839,"ParentUID":12531780,"TransformType":1,"Name":"Canvas","Components":[{"Type":-2,"GameObject UID":1655619839,"Translation":[0,0,0],"Value":[0,0,0],"Rotation":[1,0,0,0],"Scale":[1,1,1],"Width":1920,"Height":1017,"Enable":true},{"Type":4,"GameObject UID":1655619839,"Draw_load":true,"Enable":true}]},{"UID":492405005,"ParentUID":1655619839,"TransformType":1,"Name":"Panel","Components":[{"Type":-2,"GameObject UID":492405005,"Translation":[910,458.5,0],"Value":[910,458.5,0],"Rotation":[1,0,0,0],"Scale":[1,1,1],"Width":100,"Height":100,"Enable":true},{"Type":5,"GameObject UID":492405005,"Enable":true},{"Type":8,"GameObject UID":492405005,"ResourceType":1,"Resource UID":731871607,"Enable":true},{"Type":11,"GameObject UID":492405005,"Center":true,"f1_button":false,"Dragable":false,"Enable":true}]},{"UID":1869288060,"ParentUID":1655619839,"TransformType":1,"Name":"Panel","Components":[{"Type":-2,"GameObject UID":1869288060,"Translation":[177.00001525878906,133.5,0],"Value":[177.00001525878906,133.5,0],"Rotation":[1,0,0,0],"Scale":[1,1,1],"Width":473.00003051757813,"Height":563,"Enable":true},{"Type":5,"GameObject UID":1869288060,"Enable":true},{"Type":8,"GameObject UID":1869288060,"ResourceType":1,"Resource UID":69927915,"Enable":true},{"Type":11,"GameObject UID":1869288060,"Center":false,"f1_button":true,"Dragable":true,"Enable":true}]},{"UID":860402663,"ParentUID":1869288060,"TransformType":1,"Name":"Check Box","Components":[{"Type":-2,"GameObject UID":860402663,"Translation":[339.00003051757813,31.000001907348633,0],"Value":[339.00003051757813,31.000001907348633,0],"Rotation":[1,0,0,0],"Scale":[1,1,1],"Width":77,"Height":77,"Enable":true},{"Type":5,"GameObject UID":860402663,"Enable":true},{"Type":8,"GameObject UID":860402663,"ResourceType":1,"Resource UID":1193229905,"Enable":true},{"Type":10,"GameObject UID":860402663,"ResourceHoverType":1,"ResourcePressedType":1,"Resource Hover UID":1193229905,"Resource Pressed UID":2094138342,"Actived":false,"Function Selection":0,"Enable":true}]},{"UID":1791516195,"ParentUID":860402663,"TransformType":1,"Name":"Text","Components":[{"Type":-2,"GameObject UID":1791516195,"Translation":[-229.00001525878906,17,0],"Value":[-229.00001525878906,17,0],"Rotation":[1,0,0,0],"Scale":[1,1,1],"Width":100,"Height":100,"Enable":true},{"Type":5,"GameObject UID":1791516195,"Enable":true},{"Type":6,"GameObject UID":1791516195,"ResourceType":4,"Resource UID":17647166,"Font Size":50,"InputText":"V-SYNC","TextStr":"V-SYNC","Max Input":20,"Enable":true}]},{"UID":1102648438,"ParentUID":1869288060,"TransformType":1,"Name":"Check Box","Components":[{"Type":-2,"GameObject UID":1102648438,"Translation":[339.00003051757813,154,0],"Value":[339.00003051757813,154,0],"Rotation":[1,0,0,0],"Scale":[1,1,1],"Width":77,"Height":77,"Enable":true},{"Type":5,"GameObject UID":1102648438,"Enable":true},{"Type":8,"GameObject UID":1102648438,"ResourceType":1,"Resource UID":1193229905,"Enable":true},{"Type":10,"GameObject UID":1102648438,"ResourceHoverType":1,"ResourcePressedType":1,"Resource Hover UID":1193229905,"Resource Pressed UID":2094138342,"Actived":false,"Function Selection":1,"Enable":true}]},{"UID":2026691339,"ParentUID":1102648438,"TransformType":1,"Name":"Text","Components":[{"Type":-2,"GameObject UID":2026691339,"Translation":[-264,17,0],"Value":[-264,17,0],"Rotation":[1,0,0,0],"Scale":[1,1,1],"Width":100,"Height":100,"Enable":true},{"Type":5,"GameObject UID":2026691339,"Enable":true},{"Type":6,"GameObject UID":2026691339,"ResourceType":4,"Resource UID":17647166,"Font Size":50,"InputText":"CULL FACE","TextStr":"CULL FACE","Max Input":20,"Enable":true}]},{"UID":1157317375,"ParentUID":1869288060,"TransformType":1,"Name":"Text","Components":[{"Type":-2,"GameObject UID":1157317375,"Translation":[146,290,0],"Value":[146,290,0],"Rotation":[1,0,0,0],"Scale":[1,1,1],"Width":100,"Height":100,"Enable":true},{"Type":5,"GameObject UID":1157317375,"Enable":true},{"Type":6,"GameObject UID":1157317375,"ResourceType":4,"Resource UID":17647166,"Font Size":50,"InputText":"Drag it!","TextStr":"Drag it!","Max Input":20,"Enable":true}]},{"UID":1810961442,"ParentUID":1655619839,"TransformType":1,"Name":"Image","Components":[{"Type":-2,"GameObject UID":1810961442,"Translation":[-1,0,0],"Value":[-1,0,0],"Rotation":[1,0,0,0],"Scale":[1,1,1],"Width":1920.0001220703125,"Height":1021.0000610351563,"Enable":true},{"Type":5,"GameObject UID":1810961442,"Enable":true},{"Type":8,"GameObject UID":1810961442,"ResourceType":1,"Resource UID":2102531684,"Enable":true}]},{"UID":1158956064,"ParentUID":1810961442,"TransformType":1,"Name":"Button","Components":[{"Type":-2,"GameObject UID":1158956064,"Translation":[826.00006103515625,730.00006103515625,0],"Value":[826.00006103515625,730.00006103515625,0],"Rotation":[1,0,0,0],"Scale":[1,1,1],"Width":277,"Height":118.00000762939453,"Enable":true},{"Type":5,"GameObject UID":1158956064,"Enable":true},{"Type":8,"GameObject UID":1158956064,"ResourceType":1,"Resource UID":1087977457,"Enable":true},{"Type":9,"GameObject UID":1158956064,"ResourceOverType":1,"ResourceClickType":1,"Resource Over UID":640382835,"Resource Click UID":1509444885,"Function Selection":0,"Enable":true}]},{"UID":1721629266,"ParentUID":1810961442,"TransformType":1,"Name":"Image","Components":[{"Type":-2,"GameObject UID":1721629266,"Translation":[800.00006103515625,641,0],"Value":[800.00006103515625,641,0],"Rotation":[1,0,0,0],"Scale":[1,1,1],"Width":348.00003051757813,"Height":88.000007629394531,"Enable":true},{"Type":5,"GameObject UID":1721629266,"Enable":true},{"Type":8,"GameObject UID":1721629266,"ResourceType":1,"Resource UID":107524327,"Enable":true}]},{"UID":1195589514,"ParentUID":1721629266,"TransformType":1,"Name":"Input Text","Components":[{"Type":-2,"GameObject UID":1195589514,"Translation":[7.0000004768371582,17,0],"Value":[7.0000004768371582,17,0],"Rotation":[1,0,0,0],"Scale":[1,1,1],"Width":348,"Height":88,"Enable":true},{"Type":5,"GameObject UID":1195589514,"Enable":true},{"Type":6,"GameObject UID":1195589514,"ResourceType":4,"Resource UID":17647166,"Font Size":50,"InputText":"Insert your name","TextStr":"Insert your name","Max Input":20,"Enable":true},{"Type":7,"GameObject UID":1195589514,"Enable":true}]},{"UID":926522164,"ParentUID":12531780,"TransformType":0,"Name":"RootNode","Components":[{"Type":-1,"GameObject UID":926522164,"Translation":[0,0,0],"Rotation":[1,0,0,0],"Scale":[1,1,1],"Enable":true}]},{"UID":1433274905,"ParentUID":926522164,"TransformType":0,"Name":"Sky001_$AssimpFbx$_Translation","Components":[{"Type":-1,"GameObject UID":1433274905,"Translation":[18.153732299804688,0,58.960910797119141],"Rotation":[1,0,0,0],"Scale":[1,1,1],"Enable":true}]},{"UID":1057019503,"ParentUID":1433274905,"TransformType":0,"Name":"Sky001_$AssimpFbx$_PreRotation","Components":[{"Type":-1,"GameObject UID":1057019503,"Translation":[0,0,0],"Rotation":[0.70710676908493042,-0.70710676908493042,0,0],"Scale":[1,1,1],"Enable":true}]},{"UID":785202967,"ParentUID":1057019503,"TransformType":0,"Name":"Sky001_$AssimpFbx$_PostRotation","Components":[{"Type":-1,"GameObject UID":785202967,"Translation":[0,0,0],"Rotation":[0.70710676908493042,-0.70710676908493042,0,0],"Scale":[1,1,1],"Enable":true}]},{"UID":272047475,"ParentUID":785202967,"TransformType":0,"Name":"Sky001","Components":[{"Type":-1,"GameObject UID":272047475,"Translation":[0,0,0],"Rotation":[1,0,0,0],"Scale":[1,1,1],"Enable":true}]},{"UID":1558974082,"ParentUID":926522164,"TransformType":0,"Name":"Dummy001_$AssimpFbx$_PreRotation","Components":[{"Type":-1,"GameObject UID":1558974082,"Translation":[0,0,0],"Rotation":[0.70710676908493042,-0.70710676908493042,0,0],"Scale":[1,1,1],"Enable":true}]},{"UID":1363559895,"ParentUID":1558974082,"TransformType":0,"Name":"Dummy001_$AssimpFbx$_Rotation","Components":[{"Type":-1,"GameObject UID":1363559895,"Translation":[0,0,0],"Rotation":[1,0,0,0],"Scale":[1,1,1],"Enable":true}]},{"UID":741350513,"ParentUID":1363559895,"TransformType":0,"Name":"Dummy001","Components":[{"Type":-1,"GameObject UID":741350513,"Translation":[0,0,0],"Rotation":[1,0,0,0],"Scale":[1,1,1],"Enable":true}]},{"UID":942093575,"ParentUID":741350513,"TransformType":0,"Name":"City_building_004","Components":[{"Type":-1,"GameObject UID":942093575,"Translation":[-41.47589111328125,21.01409912109375,0],"Rotation":[1,0,0,0],"Scale":[1,1,1],"Enable":true},{"Type":1,"GameObject UID":942093575,"ResourceType":2,"Resource UID":1698442485,"Enable":true},{"Type":2,"GameObject UID":942093575,"Textures":[{"ResourceType":1,"Resource UID":600860838}],"ResourceType":1,"Enable":true}]},{"UID":1051238401,"ParentUID":741350513,"TransformType":0,"Name":"City_building_001","Components":[{"Type":-1,"GameObject UID":1051238401,"Translation":[17.707164764404297,20.053276062011719,2.1210729528320371e-07],"Rotation":[1,0,0,0],"Scale":[1,1,1],"Enable":true},{"Type":1,"GameObject UID":1051238401,"ResourceType":2,"Resource UID":1950239930,"Enable":true},{"Type":2,"GameObject UID":1051238401,"Textures":[{"ResourceType":1,"Resource UID":940687602}],"ResourceType":1,"Enable":true}]},{"UID":2026026261,"ParentUID":741350513,"TransformType":0,"Name":"City_building_007","Components":[{"Type":-1,"GameObject UID":2026026261,"Translation":[16.010492324829102,37.4932861328125,-1.5106878663573298e-06],"Rotation":[1,0,0,0],"Scale":[1,1,1],"Enable":true},{"Type":1,"GameObject UID":2026026261,"ResourceType":2,"Resource UID":1052197739,"Enable":true},{"Type":2,"GameObject UID":2026026261,"Textures":[{"ResourceType":1,"Resource UID":810939189}],"ResourceType":1,"Enable":true}]},{"UID":805931180,"ParentUID":741350513,"TransformType":0,"Name":"City_building_008","Components":[{"Type":-1,"GameObject UID":805931180,"Translation":[40.979995727539063,18.270824432373047,-2.0522466002148576e-06],"Rotation":[0.70710676908493042,0,0,0.70710676908493042],"Scale":[1,1,1],"Enable":true},{"Type":1,"GameObject UID":805931180,"ResourceType":2,"Resource UID":1190637711,"Enable":true},{"Type":2,"GameObject UID":805931180,"Textures":[{"ResourceType":1,"Resource UID":893915151}],"ResourceType":1,"Enable":true}]},{"UID":281953964,"ParentUID":741350513,"TransformType":0,"Name":"Line002","Components":[{"Type":-1,"GameObject UID":281953964,"Translation":[-2.1597719192504883,1.8538382053375244,0],"Rotation":[0.70710676908493042,0,0,-0.70710676908493042],"Scale":[1,1,1],"Enable":true},{"Type":1,"GameObject UID":281953964,"ResourceType":2,"Resource UID":1530010306,"Enable":true},{"Type":2,"GameObject UID":281953964,"Textures":[],"Enable":true}]},{"UID":1916394064,"ParentUID":741350513,"TransformType":0,"Name":"Plane001","Components":[{"Type":-1,"GameObject UID":1916394064,"Translation":[-0.02860260009765625,0.026032090187072754,0],"Rotation":[1,0,0,0],"Scale":[0.99663525819778442,0.97061645984649658,0.99663525819778442],"Enable":true},{"Type":1,"GameObject UID":1916394064,"ResourceType":2,"Resource UID":957243149,"Enable":true},{"Type":2,"GameObject UID":1916394064,"Textures":[],"Enable":true}]},{"UID":259625281,"ParentUID":741350513,"TransformType":0,"Name":"City_building_010","Components":[{"Type":-1,"GameObject UID":259625281,"Translation":[25.154010772705078,-39.153720855712891,8.5538641769744572e-07],"Rotation":[0.70710676908493042,0,0,0.70710676908493042],"Scale":[1,1,1],"Enable":true}]},{"UID":1831702,"ParentUID":741350513,"TransformType":0,"Name":"0","Components":[{"Type":-1,"GameObject UID":1831702,"Translation":[25.154010772705078,-39.153720855712891,8.5538641769744572e-07],"Rotation":[0.70710676908493042,0,0,0.70710676908493042],"Scale":[1,1,1],"Enable":true}]},{"UID":823389769,"ParentUID":741350513,"TransformType":0,"Name":"1","Components":[{"Type":-1,"GameObject UID":823389769,"Translation":[25.154010772705078,-39.153720855712891,8.5538641769744572e-07],"Rotation":[0.70710676908493042,0,0,0.70710676908493042],"Scale":[1,1,1],"Enable":true},{"Type":1,"GameObject UID":823389769,"ResourceType":2,"Resource UID":1957923397,"Enable":true},{"Type":2,"GameObject UID":823389769,"Textures":[{"ResourceType":1,"Resource UID":1321689393}],"ResourceType":1,"Enable":true}]},{"UID":290634531,"ParentUID":741350513,"TransformType":0,"Name":"City_building_011","Components":[{"Type":-1,"GameObject UID":290634531,"Translation":[30.134540557861328,37.4932861328125,-1.5106878663573298e-06],"Rotation":[1,0,0,0],"Scale":[1,1,1],"Enable":true},{"Type":1,"GameObject UID":290634531,"ResourceType":2,"Resource UID":1052197739,"Enable":true},{"Type":2,"GameObject UID":290634531,"Textures":[{"ResourceType":1,"Resource UID":810939189}],"ResourceType":1,"Enable":true}]},{"UID":675760717,"ParentUID":741350513,"TransformType":0,"Name":"City_building_013","Components":[{"Type":-1,"GameObject UID":675760717,"Translation":[-42.288055419921875,33.201576232910156,5.0146070407208754e-07],"Rotation":[0.70710676908493042,0,0,0.70710676908493042],"Scale":[1,1,1],"Enable":true},{"Type":1,"GameObject UID":675760717,"ResourceType":2,"Resource UID":767011870,"Enable":true},{"Type":2,"GameObject UID":675760717,"Textures":[{"ResourceType":1,"Resource UID":1487404317}],"ResourceType":1,"Enable":true}]},{"UID":65139781,"ParentUID":741350513,"TransformType":0,"Name":"City_building_014","Components":[{"Type":-1,"GameObject UID":65139781,"Translation":[-19.439706802368164,32.061729431152344,0],"Rotation":[-4.3711388286737929e-08,0,0,1],"Scale":[1,1,1],"Enable":true},{"Type":1,"GameObject UID":65139781,"ResourceType":2,"Resource UID":163804075,"Enable":true},{"Type":2,"GameObject UID":65139781,"Textures":[{"ResourceType":1,"Resource UID":600860838}],"ResourceType":1,"Enable":true}]},{"UID":1758714184,"ParentUID":741350513,"TransformType":0,"Name":"City_building_016","Components":[{"Type":-1,"GameObject UID":1758714184,"Translation":[34.270423889160156,-41.972747802734375,8.5538641769744572e-07],"Rotation":[-4.3711388286737929e-08,0,0,1],"Scale":[1,1,1],"Enable":true}]},{"UID":365103265,"ParentUID":741350513,"TransformType":0,"Name":"0","Components":[{"Type":-1,"GameObject UID":365103265,"Translation":[34.270423889160156,-41.972747802734375,8.5538641769744572e-07],"Rotation":[-4.3711388286737929e-08,0,0,1],"Scale":[1,1,1],"Enable":true}]},{"UID":1237966673,"ParentUID":741350513,"TransformType":0,"Name":"1","Components":[{"Type":-1,"GameObject UID":1237966673,"Translation":[34.270423889160156,-41.972747802734375,8.5538641769744572e-07],"Rotation":[-4.3711388286737929e-08,0,0,1],"Scale":[1,1,1],"Enable":true},{"Type":1,"GameObject UID":1237966673,"ResourceType":2,"Resource UID":1957923397,"Enable":true},{"Type":2,"GameObject UID":1237966673,"Textures":[{"ResourceType":1,"Resource UID":1321689393}],"ResourceType":1,"Enable":true}]},{"UID":1369052235,"ParentUID":741350513,"TransformType":0,"Name":"City_building_017","Components":[{"Type":-1,"GameObject UID":1369052235,"Translation":[44.260082244873047,-39.153720855712891,8.5538641769744572e-07],"Rotation":[0.70710676908493042,0,0,0.70710676908493042],"Scale":[1,1,1],"Enable":true}]},{"UID":871464487,"ParentUID":741350513,"TransformType":0,"Name":"0","Components":[{"Type":-1,"GameObject UID":871464487,"Translation":[44.260082244873047,-39.153720855712891,8.5538641769744572e-07],"Rotation":[0.70710676908493042,0,0,0.70710676908493042],"Scale":[1,1,1],"Enable":true}]},{"UID":1521054383,"ParentUID":741350513,"TransformType":0,"Name":"1","Components":[{"Type":-1,"GameObject UID":1521054383,"Translation":[44.260082244873047,-39.153720855712891,8.5538641769744572e-07],"Rotation":[0.70710676908493042,0,0,0.70710676908493042],"Scale":[1,1,1],"Enable":true},{"Type":1,"GameObject UID":1521054383,"ResourceType":2,"Resource UID":1957923397,"Enable":true},{"Type":2,"GameObject UID":1521054383,"Textures":[{"ResourceType":1,"Resource UID":1321689393}],"ResourceType":1,"Enable":true}]},{"UID":613597979,"ParentUID":741350513,"TransformType":0,"Name":"City_building_022","Components":[{"Type":-1,"GameObject UID":613597979,"Translation":[-20.831323623657227,-27.426488876342773,0],"Rotation":[1.9470718370939721e-07,0,0,1],"Scale":[1,1,1],"Enable":true},{"Type":1,"GameObject UID":613597979,"ResourceType":2,"Resource UID":1882653394,"Enable":true},{"Type":2,"GameObject UID":613597979,"Textures":[{"ResourceType":1,"Resource UID":1269590527}],"ResourceType":1,"Enable":true}]},{"UID":1560189835,"ParentUID":741350513,"TransformType":0,"Name":"City_building_023","Components":[{"Type":-1,"GameObject UID":1560189835,"Translation":[42.130641937255859,37.4932861328125,-1.5106878663573298e-06],"Rotation":[1,0,0,0],"Scale":[1,1,1],"Enable":true},{"Type":1,"GameObject UID":1560189835,"ResourceType":2,"Resource UID":1052197739,"Enable":true},{"Type":2,"GameObject UID":1560189835,"Textures":[{"ResourceType":1,"Resource UID":810939189}],"ResourceType":1,"Enable":true}]},{"UID":106153628,"ParentUID":741350513,"TransformType":0,"Name":"City_building_024","Components":[{"Type":-1,"GameObject UID":106153628,"Translation":[-20.572771072387695,43.060829162597656,-0.069194458425045013],"Rotation":[4.3711388286737929e-08,0,0,1],"Scale":[1,1,1],"Enable":true},{"Type":1,"GameObject UID":106153628,"ResourceType":2,"Resource UID":1190637711,"Enable":true},{"Type":2,"GameObject UID":106153628,"Textures":[{"ResourceType":1,"Resource UID":893915151}],"ResourceType":1,"Enable":true}]},{"UID":1030505661,"ParentUID":741350513,"TransformType":0,"Name":"City_building_026","Components":[{"Type":-1,"GameObject UID":1030505661,"Translation":[31.51188850402832,-16.446016311645508,0],"Rotation":[4.3711388286737929e-08,0,0,1],"Scale":[1,1,1],"Enable":true},{"Type":1,"GameObject UID":1030505661,"ResourceType":2,"Resource UID":379122145,"Enable":true},{"Type":2,"GameObject UID":1030505661,"Textures":[{"ResourceType":1,"Resource UID":1269590527}],"ResourceType":1,"Enable":true}]},{"UID":1700945505,"ParentUID":741350513,"TransformType":0,"Name":"City_building_028","Components":[{"Type":-1,"GameObject UID":1700945505,"Translation":[13.38798999786377,-33.755039215087891,-9.3834518111179932e-07],"Rotation":[1,0,0,0],"Scale":[1,1,1],"Enable":true},{"Type":1,"GameObject UID":1700945505,"ResourceType":2,"Resource UID":1599007227,"Enable":true},{"Type":2,"GameObject UID":1700945505,"Textures":[{"ResourceType":1,"Resource UID":1281369374}],"ResourceType":1,"Enable":true}]},{"UID":688773437,"ParentUID":741350513,"TransformType":0,"Name":"Object010","Components":[{"Type":-1,"GameObject UID":688773437,"Translation":[-2.5033531188964844,15.800846099853516,0],"Rotation":[1,0,0,0],"Scale":[1,1,1],"Enable":true},{"Type":1,"GameObject UID":688773437,"ResourceType":2,"Resource UID":555760798,"Enable":true},{"Type":2,"GameObject UID":688773437,"Textures":[],"Enable":true}]},{"UID":1933103514,"ParentUID":741350513,"TransformType":0,"Name":"City_building_030","Components":[{"Type":-1,"GameObject UID":1933103514,"Translation":[-42.807239532470703,-41.835563659667969,-9.3834518111179932e-07],"Rotation":[0.70710676908493042,0,0,-0.70710676908493042],"Scale":[1,1,1],"Enable":true},{"Type":1,"GameObject UID":1933103514,"ResourceType":2,"Resource UID":1599007227,"Enable":true},{"Type":2,"GameObject UID":1933103514,"Textures":[{"ResourceType":1,"Resource UID":1281369374}],"ResourceType":1,"Enable":true}]},{"UID":1799590704,"ParentUID":741350513,"TransformType":0,"Name":"City_building_031","Components":[{"Type":-1,"GameObject UID":1799590704,"Translation":[-34.679481506347656,-41.835563659667969,-9.3834518111179932e-07],"Rotation":[0.70710676908493042,0,0,-0.70710676908493042],"Scale":[1,1,1],"Enable":true},{"Type":1,"GameObject UID":1799590704,"ResourceType":2,"Resource UID":1599007227,"Enable":true},{"Type":2,"GameObject UID":1799590704,"Textures":[{"ResourceType":1,"Resource UID":1281369374}],"ResourceType":1,"Enable":true}]},{"UID":813469910,"ParentUID":741350513,"TransformType":0,"Name":"City_building_032","Components":[{"Type":-1,"GameObject UID":813469910,"Translation":[-29.478403091430664,21.01409912109375,0],"Rotation":[1,0,0,0],"Scale":[1,1,1],"Enable":true},{"Type":1,"GameObject UID":813469910,"ResourceType":2,"Resource UID":1698442485,"Enable":true},{"Type":2,"GameObject UID":813469910,"Textures":[{"ResourceType":1,"Resource UID":600860838}],"ResourceType":1,"Enable":true}]},{"UID":1149865426,"ParentUID":741350513,"TransformType":0,"Name":"City_building_033","Components":[{"Type":-1,"GameObject UID":1149865426,"Translation":[-32.361495971679688,42.37042236328125,5.0146070407208754e-07],"Rotation":[1,0,0,0],"Scale":[1,1,1],"Enable":true},{"Type":1,"GameObject UID":1149865426,"ResourceType":2,"Resource UID":1390348819,"Enable":true},{"Type":2,"GameObject UID":1149865426,"Textures":[{"ResourceType":1,"Resource UID":1487404317}],"ResourceType":1,"Enable":true}]},{"UID":885430680,"ParentUID":741350513,"TransformType":0,"Name":"City_building_034","Components":[{"Type":-1,"GameObject UID":885430680,"Translation":[16.049516677856445,-16.696884155273438,0],"Rotation":[0.70710670948028564,0,0,-0.7071068286895752],"Scale":[1,1,1],"Enable":true},{"Type":1,"GameObject UID":885430680,"ResourceType":2,"Resource UID":1308366286,"Enable":true},{"Type":2,"GameObject UID":885430680,"Textures":[{"ResourceType":1,"Resource UID":1269590527}],"ResourceType":1,"Enable":true}]},{"UID":1051285145,"ParentUID":741350513,"TransformType":0,"Name":"City_building_035","Components":[{"Type":-1,"GameObject UID":1051285145,"Translation":[13.38798999786377,-40.802516937255859,-9.3834518111179932e-07],"Rotation":[1,0,0,0],"Scale":[1,1,1],"Enable":true},{"Type":1,"GameObject UID":1051285145,"ResourceType":2,"Resource UID":1599007227,"Enable":true},{"Type":2,"GameObject UID":1051285145,"Textures":[{"ResourceType":1,"Resource UID":1281369374}],"ResourceType":1,"Enable":true}]},{"UID":985422991,"ParentUID":741350513,"TransformType":0,"Name":"City_building_036","Components":[{"Type":-1,"GameObject UID":985422991,"Translation":[-31.216331481933594,33.201576232910156,5.0146070407208754e-07],"Rotation":[0.70710676908493042,0,0,-0.70710676908493042],"Scale":[1,1,1],"Enable":true},{"Type":1,"GameObject UID":985422991,"ResourceType":2,"Resource UID":767011870,"Enable":true},{"Type":2,"GameObject UID":985422991,"Textures":[{"ResourceType":1,"Resource UID":1487404317}],"ResourceType":1,"Enable":true}]},{"UID":473985702,"ParentUID":741350513,"TransformType":0,"Name":"City_building_037","Components":[{"Type":-1,"GameObject UID":473985702,"Translation":[-20.317693710327148,-16.163608551025391,0],"Rotation":[1.9470718370939721e-07,0,0,1],"Scale":[1,1,1],"Enable":true},{"Type":1,"GameObject UID":473985702,"ResourceType":2,"Resource UID":1001180651,"Enable":true},{"Type":2,"GameObject UID":473985702,"Textures":[{"ResourceType":1,"Resource UID":1269590527}],"ResourceType":1,"Enable":true}]},{"UID":1124839140,"ParentUID":741350513,"TransformType":0,"Name":"City_building_038","Components":[{"Type":-1,"GameObject UID":1124839140,"Translation":[-41.649002075195313,-16.495393753051758,0],"Rotation":[0.70710670948028564,0,0,-0.7071068286895752],"Scale":[1,1,1],"Enable":true},{"Type":1,"GameObject UID":1124839140,"ResourceType":2,"Resource UID":956921706,"Enable":true},{"Type":2,"GameObject UID":1124839140,"Textures":[{"ResourceType":1,"Resource UID":1269590527}],"ResourceType":1,"Enable":true}]},{"UID":139610791,"ParentUID":741350513,"TransformType":0,"Name":"City_building_039","Components":[{"Type":-1,"GameObject UID":139610791,"Translation":[-42.807239532470703,-30.643888473510742,-9.3834518111179932e-07],"Rotation":[0.70710676908493042,0,0,-0.70710676908493042],"Scale":[1,1,1],"Enable":true},{"Type":1,"GameObject UID":139610791,"ResourceType":2,"Resource UID":1599007227,"Enable":true},{"Type":2,"GameObject UID":139610791,"Textures":[{"ResourceType":1,"Resource UID":1281369374}],"ResourceType":1,"Enable":true}]},{"UID":331893889,"ParentUID":741350513,"TransformType":0,"Name":"City_building_040","Components":[{"Type":-1,"GameObject UID":331893889,"Translation":[-34.679481506347656,-30.643888473510742,-9.3834518111179932e-07],"Rotation":[0.70710676908493042,0,0,-0.70710676908493042],"Scale":[1,1,1],"Enable":true},{"Type":1,"GameObject UID":331893889,"ResourceType":2,"Resource UID":1599007227,"Enable":true},{"Type":2,"GameObject UID":331893889,"Textures":[{"ResourceType":1,"Resource UID":1281369374}],"ResourceType":1,"Enable":true}]},{"UID":2007887996,"ParentUID":741350513,"TransformType":0,"Name":"City_building_041","Components":[{"Type":-1,"GameObject UID":2007887996,"Translation":[30.695278167724609,21.612646102905273,2.1210729528320371e-07],"Rotation":[0.70710676908493042,0,0,0.70710676908493042],"Scale":[1,1,1],"Enable":true},{"Type":1,"GameObject UID":2007887996,"ResourceType":2,"Resource UID":1950239930,"Enable":true},{"Type":2,"GameObject UID":2007887996,"Textures":[{"ResourceType":1,"Resource UID":940687602}],"ResourceType":1,"Enable":true}]},{"UID":722168051,"ParentUID":926522164,"TransformType":0,"Name":"Camera001_$AssimpFbx$_Translation","Components":[{"Type":-1,"GameObject UID":722168051,"Translation":[-78.312431335449219,45.251216888427734,-97.031112670898438],"Rotation":[1,0,0,0],"Scale":[1,1,1],"Enable":true}]},{"UID":1174735107,"ParentUID":722168051,"TransformType":0,"Name":"Camera001_$AssimpFbx$_PreRotation","Components":[{"Type":-1,"GameObject UID":1174735107,"Translation":[0,0,0],"Rotation":[0.70710676908493042,-0.70710676908493042,0,0],"Scale":[1,1,1],"Enable":true}]},{"UID":1465672099,"ParentUID":1174735107,"TransformType":0,"Name":"Camera001_$AssimpFbx$_Rotation","Components":[{"Type":-1,"GameObject UID":1465672099,"Translation":[0,0,0],"Rotation":[-0.26833298802375793,-0.19855600595474243,0.56070470809936523,0.75774872303009033],"Scale":[1,0.99999994039535522,0.99999994039535522],"Enable":true}]},{"UID":1724233627,"ParentUID":1465672099,"TransformType":0,"Name":"Camera001","Components":[{"Type":-1,"GameObject UID":1724233627,"Translation":[0,0,0],"Rotation":[1,0,0,0],"Scale":[1,1,1],"Enable":true}]},{"UID":680961714,"ParentUID":926522164,"TransformType":0,"Name":"Camera001.Target_$AssimpFbx$_Translation","Components":[{"Type":-1,"GameObject UID":680961714,"Translation":[-28.132621765136719,20.873329162597656,-35.064212799072266],"Rotation":[1,0,0,0],"Scale":[1,1,1],"Enable":true}]},{"UID":1386499222,"ParentUID":680961714,"TransformType":0,"Name":"Camera001.Target_$AssimpFbx$_PreRotation","Components":[{"Type":-1,"GameObject UID":1386499222,"Translation":[0,0,0],"Rotation":[0.70710676908493042,-0.70710676908493042,0,0],"Scale":[1,1,1],"Enable":true}]},{"UID":72402212,"ParentUID":1386499222,"TransformType":0,"Name":"Camera001.Target_$AssimpFbx$_Rotation","Components":[{"Type":-1,"GameObject UID":72402212,"Translation":[0,0,0],"Rotation":[-0.26833304762840271,-0.19855606555938721,0.56070470809936523,0.75774872303009033],"Scale":[1,0.99999994039535522,1],"Enable":true}]},{"UID":570282143,"ParentUID":72402212,"TransformType":0,"Name":"Camera001.Target","Components":[{"Type":-1,"GameObject UID":570282143,"Translation":[0,0,0],"Rotation":[1,0,0,0],"Scale":[1,1,1],"Enable":true}]},{"UID":935412067,"ParentUID":926522164,"TransformType":0,"Name":"Spot001_$AssimpFbx$_Translation","Components":[{"Type":-1,"GameObject UID":935412067,"Translation":[-66.721267700195313,141.93412780761719,6.2041376622801181e-06],"Rotation":[1,0,0,0],"Scale":[1,1,1],"Enable":true}]},{"UID":1881921332,"ParentUID":935412067,"TransformType":0,"Name":"Spot001_$AssimpFbx$_PreRotation","Components":[{"Type":-1,"GameObject UID":1881921332,"Translation":[0,0,0],"Rotation":[0.70710676908493042,-0.70710676908493042,0,0],"Scale":[1,1,1],"Enable":true}]},{"UID":1120268055,"ParentUID":1881921332,"TransformType":0,"Name":"Spot001_$AssimpFbx$_Rotation","Components":[{"Type":-1,"GameObject UID":1120268055,"Translation":[0,0,0],"Rotation":[0.69003516435623169,0.15443940460681915,-0.15443937480449677,-0.69003510475158691],"Scale":[1,1,1],"Enable":true}]},{"UID":1871165409,"ParentUID":1120268055,"TransformType":0,"Name":"Spot001_$AssimpFbx$_PostRotation","Components":[{"Type":-1,"GameObject UID":1871165409,"Translation":[0,0,0],"Rotation":[0.70710676908493042,-0.70710676908493042,0,0],"Scale":[1,1,1],"Enable":true}]},{"UID":1753945675,"ParentUID":1871165409,"TransformType":0,"Name":"Spot001","Components":[{"Type":-1,"GameObject UID":1753945675,"Translation":[0,0,0],"Rotation":[1,0,0,0],"Scale":[1,1,1],"Enable":true}]},{"UID":1236703461,"ParentUID":926522164,"TransformType":0,"Name":"Spot001.Target_$AssimpFbx$_Translation","Components":[{"Type":-1,"GameObject UID":1236703461,"Translation":[28.890945434570313,-60.963882446289063,-2.6648158382158726e-06],"Rotation":[1,0,0,0],"Scale":[1,1,1],"Enable":true}]},{"UID":1469799110,"ParentUID":1236703461,"TransformType":0,"Name":"Spot001.Target_$AssimpFbx$_PreRotation","Components":[{"Type":-1,"GameObject UID":1469799110,"Translation":[0,0,0],"Rotation":[0.70710676908493042,-0.70710676908493042,0,0],"Scale":[1,1,1],"Enable":true}]},{"UID":1288057760,"ParentUID":1469799110,"TransformType":0,"Name":"Spot001.Target_$AssimpFbx$_Rotation","Components":[{"Type":-1,"GameObject UID":1288057760,"Translation":[0,0,0],"Rotation":[0.70710670948028564,0.7071068286895752,0,0],"Scale":[1,1,1],"Enable":true}]},{"UID":1247177534,"ParentUID":1288057760,"TransformType":0,"Name":"Spot001.Target","Components":[{"Type":-1,"GameObject UID":1247177534,"Translation":[0,0,0],"Rotation":[1,0,0,0],"Scale":[1,1,1],"Enable":true}]}]}